latexcheck/__init__.py
latexcheck/helpers/__init__.py
latexcheck-1.2.6.dist-info/METADATA
latexcheck-1.2.6.dist-info/WHEEL
latexcheck-1.2.6.dist-info/entry_points.txt
latexcheck-1.2.6.dist-info/top_level.txt
latexcheck-1.2.6.dist-info/RECORD
