Metadata-Version: 2.1
Name: latexcheck
Version: 1.2.6
Summary: LaTeX linter
Author-email: Alex Dainiak <dainiak@gmail.com>
Project-URL: Homepage, http://github.com/dainiak/latexcheck-py/
Classifier: License :: OSI Approved :: MIT License
Requires-Python: >=3.8
Requires-Dist: texsoup>=0.3.1
